pyconsFold/__init__.py
pyconsFold/_pyconsFold_helpers.py
pyconsFold/_pyconsFold_libs.py
pyconsFold/_qa.py
pyconsFold/run.py
pyconsFold/utils.py
pyconsFold/TMscore/LICENSE
pyconsFold/TMscore/Ref.txt
pyconsFold/TMscore/TMscore
pyconsFold/dssp/LICENSE
pyconsFold/dssp/Ref.txt
pyconsFold/dssp/dssp-2.0.4-linux-amd64
pyconsFold/pcons/LICENSE
pyconsFold/pcons/Ref.txt
pyconsFold/pcons/pcons
pyconsFold/templates/dgsa.inp
pyconsFold/templates/extn.inp
pyconsFold/templates/gseq.inp
pyconsFold/templates/scalecoolsetupedited
pyconsFold/templates/scalehotedited
pyconsFold-0.2.1.dist-info/LICENSE
pyconsFold-0.2.1.dist-info/METADATA
pyconsFold-0.2.1.dist-info/WHEEL
pyconsFold-0.2.1.dist-info/top_level.txt
pyconsFold-0.2.1.dist-info/RECORD
