Metadata-Version: 2.1
Name: pyconsFold
Version: 0.2.1
Summary: A python wrapper around CNS for modelling and docking using distance predictions, inspired by CONFOLD
Home-page: https://github.com/johnlamb/pyconsFold
Author: John Lamb
Author-email: john@biolamb.se
License: UNKNOWN
Platform: UNKNOWN
Classifier: Programming Language :: Python :: 3
Classifier: License :: OSI Approved :: GNU Lesser General Public License v3 or later (LGPLv3+)
Classifier: Operating System :: Unix
Requires-Python: >3.5
Provides-Extra: all
Requires-Dist: biopython (>=1.7) ; extra == 'all'
Requires-Dist: numpy (>=1.19) ; extra == 'all'
Requires-Dist: scipy (>=1.4.0) ; extra == 'all'
